[{"id":"d4e0edee.b41d","type":"tab","label":"Flow 1","disabled":false,"info":""},{"id":"c49046a8.f452d8","type":"osc","z":"d4e0edee.b41d","name":"","path":"","metadata":false,"x":513.0234375,"y":787.0390625,"wires":[["d50b0fc0.3c06d"]]},{"id":"d50b0fc0.3c06d","type":"udp out","z":"d4e0edee.b41d","name":"","addr":"127.0.0.1","iface":"","port":"3333","ipv":"udp4","outport":"","base64":false,"multicast":"false","x":693.0234375,"y":787.0390625,"wires":[]},{"id":"8976a650.5ffa18","type":"ui_slider","z":"d4e0edee.b41d","name":"","label":"slider","group":"37349233.c38cbe","order":0,"width":0,"height":0,"passthru":false,"topic":"/dial","min":0,"max":"127","step":1,"x":308.53906631469727,"y":710.4062786102295,"wires":[["c49046a8.f452d8"]]},{"id":"55032a0c.a5a8f4","type":"udp in","z":"d4e0edee.b41d","name":"","iface":"","port":"3334","ipv":"udp4","multicast":"false","group":"","datatype":"buffer","x":246.0234375,"y":335.9999977350235,"wires":[["e1a2cc18.1f2f1"]]},{"id":"e1a2cc18.1f2f1","type":"osc","z":"d4e0edee.b41d","name":"","path":"","metadata":false,"x":416.0234375,"y":335.9999977350235,"wires":[["f4af60dd.ebfdf","bf7d406b.41ec","8976a650.5ffa18"]]},{"id":"f4af60dd.ebfdf","type":"debug","z":"d4e0edee.b41d","name":"","active":true,"console":"false","complete":"false","x":596.0234375,"y":335.9999977350235,"wires":[]},{"id":"bf7d406b.41ec","type":"debug","z":"d4e0edee.b41d","name":"","active":false,"console":"false","complete":"raw","x":586.0234375,"y":395.9999977350235,"wires":[]},{"id":"37349233.c38cbe","type":"ui_group","z":"","name":"Default","tab":"d58480a6.992b3","disp":true,"width":"6","collapse":false},{"id":"d58480a6.992b3","type":"ui_tab","z":"","name":"Home","icon":"dashboard"}]